README.md
setup.py
HKH_Dev_Tools.egg-info/PKG-INFO
HKH_Dev_Tools.egg-info/SOURCES.txt
HKH_Dev_Tools.egg-info/dependency_links.txt
HKH_Dev_Tools.egg-info/entry_points.txt
HKH_Dev_Tools.egg-info/namespace_packages.txt
HKH_Dev_Tools.egg-info/requires.txt
HKH_Dev_Tools.egg-info/top_level.txt
orangecontrib/__init__.py
orangecontrib/dev_workflow/__init__.py
orangecontrib/dev_workflow/widgets/MetManagement.py
orangecontrib/dev_workflow/widgets/VarManagement.py
orangecontrib/dev_workflow/widgets/WrapMessageBox.py
orangecontrib/dev_workflow/widgets/__init__.py
orangecontrib/dev_workflow/widgets/goto.py
orangecontrib/dev_workflow/widgets/orange_sub_workflow.py
orangecontrib/dev_workflow/widgets/shared_functions.py
orangecontrib/dev_workflow/widgets/shared_variables.py
orangecontrib/dev_workflow/widgets/subworkflow_input.py
orangecontrib/dev_workflow/widgets/subworkflow_output.py
orangecontrib/dev_workflow/widgets/icons/Chatbot.svg
orangecontrib/dev_workflow/widgets/icons/DocumentEater.svg
orangecontrib/dev_workflow/widgets/icons/Embeddings.svg
orangecontrib/dev_workflow/widgets/icons/LanguageModel.svg
orangecontrib/dev_workflow/widgets/icons/TextPreprocessing.svg
orangecontrib/dev_workflow/widgets/icons/goto.png