Metadata-Version: 1.0
Name: HKH-Dev-Tools
Version: 0.2.1
Summary: Library of developed widgets
Home-page: UNKNOWN
Author: HKH
Author-email: UNKNOWN
License: UNKNOWN
Keywords: orange3 add-on
Platform: UNKNOWN
